setup.py
AiPangu/__init__.py
AiPangu/check_params.cp36-win_amd64.pyd
AiPangu/pangu.cp36-win_amd64.pyd
AiPangu/tools.cp36-win_amd64.pyd
AiPangu/check_params.pyi
AiPangu/pangu.pyi
AiPangu.egg-info/PKG-INFO
AiPangu.egg-info/SOURCES.txt
AiPangu.egg-info/dependency_links.txt
AiPangu.egg-info/requires.txt
AiPangu.egg-info/top_level.txt